README.md
setup.py
lbrlabs_pulumi_vantage/__init__.py
lbrlabs_pulumi_vantage/_utilities.py
lbrlabs_pulumi_vantage/aws_provider.py
lbrlabs_pulumi_vantage/cost_report.py
lbrlabs_pulumi_vantage/dashboard.py
lbrlabs_pulumi_vantage/folder.py
lbrlabs_pulumi_vantage/get_aws_provider.py
lbrlabs_pulumi_vantage/get_aws_provider_info.py
lbrlabs_pulumi_vantage/outputs.py
lbrlabs_pulumi_vantage/provider.py
lbrlabs_pulumi_vantage/pulumi-plugin.json
lbrlabs_pulumi_vantage/py.typed
lbrlabs_pulumi_vantage/saved_filter.py
lbrlabs_pulumi_vantage/saved_filters.py
lbrlabs_pulumi_vantage.egg-info/PKG-INFO
lbrlabs_pulumi_vantage.egg-info/SOURCES.txt
lbrlabs_pulumi_vantage.egg-info/dependency_links.txt
lbrlabs_pulumi_vantage.egg-info/not-zip-safe
lbrlabs_pulumi_vantage.egg-info/requires.txt
lbrlabs_pulumi_vantage.egg-info/top_level.txt
lbrlabs_pulumi_vantage/config/__init__.py
lbrlabs_pulumi_vantage/config/vars.py