Metadata-Version: 2.1
Name: lbrlabs-pulumi-vantage
Version: 0.0.2
Summary: A Pulumi package to create resource in vantage.sh.
Home-page: https://pulumi.io
License: Apache-2.0
Project-URL: Repository, https://github.com/lbrlabs/pulumi-vantage
Keywords: pulumi vantage
Platform: UNKNOWN
Requires-Python: >=3.7
